LICENSE.md
MANIFEST.in
README.md
setup.cfg
setup.py
submit.md
doc/.buildinfo
doc/KADMOS.html
doc/genindex.html
doc/objects.inv
doc/py-modindex.html
doc/search.html
doc/searchindex.js
doc/.doctrees/KADMOS.doctree
doc/.doctrees/environment.pickle
doc/_downloads/KADMOS_UML.pdf
doc/_downloads/3d13c952f4ae0047f7c40e9d174ea8dc/KADMOS_UML.pdf
doc/_images/KADMOS_UML.png
doc/_sources/KADMOS.rst.txt
doc/_sources/KADMOS.txt
doc/_static/ajax-loader.gif
doc/_static/alabaster.css
doc/_static/basic.css
doc/_static/classic.css
doc/_static/comment-bright.png
doc/_static/comment-close.png
doc/_static/comment.png
doc/_static/custom.css
doc/_static/doctools.js
doc/_static/documentation_options.js
doc/_static/down-pressed.png
doc/_static/down.png
doc/_static/file.png
doc/_static/jquery-1.11.1.js
doc/_static/jquery-3.1.0.js
doc/_static/jquery-3.2.1.js
doc/_static/jquery.js
doc/_static/language_data.js
doc/_static/minus.png
doc/_static/plus.png
doc/_static/pygments.css
doc/_static/searchtools.js
doc/_static/sidebar.js
doc/_static/underscore-1.3.1.js
doc/_static/underscore.js
doc/_static/up-pressed.png
doc/_static/up.png
doc/_static/websupport.js
examples/__init__.py
examples/__init__.pyc
examples/__pycache__/__init__.cpython-37.pyc
examples/journal_paper/__init__.py
examples/journal_paper/case_study.py
examples/journal_paper/sellar_example.py
examples/knowledgebases/__init__.py
examples/knowledgebases/case_study/EMWET-input.xml
examples/knowledgebases/case_study/EMWET-output.xml
examples/knowledgebases/case_study/GACA-input.xml
examples/knowledgebases/case_study/GACA-output.xml
examples/knowledgebases/case_study/HANGAR-input.xml
examples/knowledgebases/case_study/HANGAR-output.xml
examples/knowledgebases/case_study/INITIATOR-input.xml
examples/knowledgebases/case_study/INITIATOR-output.xml
examples/knowledgebases/case_study/MaCal-input.xml
examples/knowledgebases/case_study/MaCal-output.xml
examples/knowledgebases/case_study/PHALANX-input.xml
