Metadata-Version: 1.1
Name: kadmos
Version: 0.9.11
Summary: Knowledge- and graph-based Agile Design for Multidisciplinary Optimization System
Home-page: https://bitbucket.org/imcovangent/kadmos
Author: Imco van Gent
Author-email: i.vangent@tudelft.nl
License: Apache Software License
Download-URL: https://bitbucket.org/imcovangent/kadmos/raw/master/dist/0.9.11.tar.gzip
Keywords: optimization agile multidisciplinary graph engineering
Platform: UNKNOWN
Classifier: Development Status :: 4 - Beta
Classifier: License :: OSI Approved :: Apache Software License
Classifier: Programming Language :: Python
Classifier: Programming Language :: Python :: 2.7
Classifier: Programming Language :: Python :: 3.7
Classifier: Intended Audience :: Science/Research
Classifier: Topic :: Scientific/Engineering
